wirelesswizard/__init__.py
wirelesswizard/wirelesswizard.py
wirelesswizard-0.1.1a0.dist-info/LICENSE
wirelesswizard-0.1.1a0.dist-info/METADATA
wirelesswizard-0.1.1a0.dist-info/WHEEL
wirelesswizard-0.1.1a0.dist-info/top_level.txt
wirelesswizard-0.1.1a0.dist-info/RECORD
