Metadata-Version: 2.1
Name: wirelesswizard
Version: 0.1.1a0
Summary: Simple wireless interface handler
Home-page: https://github.com/mind2hex/wirelesswizard
Author: mind2hex
Author-email: neodeus8@gmail.com
License: GPLv3
Keywords: wireless,interface,WiFi,monitor,Linux,iw,iwconfig,ifconfig
Classifier: Programming Language :: Python :: 3
Classifier: License :: OSI Approved :: GNU General Public License v3 (GPLv3)
Classifier: Operating System :: POSIX :: Linux
Requires-Python: >=3.9
License-File: LICENSE
Requires-Dist: pandas
